{
  "start": 1085,
  "end": 1090,
  "version": 124,
  "docFile": "PHASE_1085_1090_GOVERNANCE_RECOVERY_ASSURANCE_CONTINUITY_V124.md",
  "testFile": "src/lib/__tests__/governance-recovery-assurance-suite-v124.test.ts",
  "title": "Governance Recovery Assurance Continuity V124",
  "modules": [
    { "phase": 1085, "title": "Governance Recovery Assurance Router V124", "fileName": "governance-recovery-assurance-router-v124.ts", "exportBase": "GovernanceRecoveryAssurance", "reportLabel": "Governance recovery assurance", "reportMessage": "Governance recovery assurance routed", "mode": "router", "signalFields": ["governanceRecovery", "assuranceCoverage", "routerCost"], "routeLabels": ["recovery-priority", "recovery-balanced", "recovery-review"] },
    { "phase": 1086, "title": "Policy Continuity Stability Harmonizer V124", "fileName": "policy-continuity-stability-harmonizer-v124.ts", "exportBase": "PolicyContinuityStability", "reportLabel": "Policy continuity stability", "reportMessage": "Policy continuity stability harmonized", "mode": "harmonizer", "signalFields": ["policyContinuity", "stabilityDepth", "harmonizerCost"] },
    { "phase": 1087, "title": "Compliance Assurance Recovery Mesh V124", "fileName": "compliance-assurance-recovery-mesh-v124.ts", "exportBase": "ComplianceAssuranceRecovery", "reportLabel": "Compliance assurance recovery", "reportMessage": "Compliance assurance recovery routed", "mode": "router", "signalFields": ["complianceAssurance", "recoveryCoverage", "meshCost"], "routeLabels": ["assurance-priority", "assurance-balanced", "assurance-review"] },
    { "phase": 1088, "title": "Trust Stability Continuity Forecaster V124", "fileName": "trust-stability-continuity-forecaster-v124.ts", "exportBase": "TrustStabilityContinuity", "reportLabel": "Trust stability continuity", "reportMessage": "Trust stability continuity forecasted", "mode": "forecaster", "signalFields": ["trustStability", "continuityDepth", "forecastCost"] },
    { "phase": 1089, "title": "Board Recovery Stability Coordinator V124", "fileName": "board-recovery-stability-coordinator-v124.ts", "exportBase": "BoardRecoveryStability", "reportLabel": "Board recovery stability", "reportMessage": "Board recovery stability coordinated", "mode": "coordinator", "signalFields": ["boardRecovery", "stabilityCoverage", "coordinationCost"] },
    { "phase": 1090, "title": "Policy Assurance Continuity Engine V124", "fileName": "policy-assurance-continuity-engine-v124.ts", "exportBase": "PolicyAssuranceContinuity", "reportLabel": "Policy assurance continuity", "reportMessage": "Policy assurance continuity evaluated", "mode": "engine", "signalFields": ["policyAssurance", "continuityDepth", "engineCost"] }
  ]
}
